pyschemaclassifier/__init__.py
pyschemaclassifier/cli.py
pyschemaclassifier/cli_verify.py
pyschemaclassifier/config.py
pyschemaclassifier/exceptions.py
pyschemaclassifier/infer.py
pyschemaclassifier/logging_utils.py
pyschemaclassifier/verify.py
pyschemaclassifier/dataframe/__init__.py
pyschemaclassifier/dataframe/pandas.py
pyschemaclassifier/dataframe/spark.py
pyschemaclassifier/detection/avro.py
pyschemaclassifier/detection/classifier.py
pyschemaclassifier/detection/compression.py
pyschemaclassifier/detection/csv.py
pyschemaclassifier/detection/delta.py
pyschemaclassifier/detection/hudi.py
pyschemaclassifier/detection/iceberg.py
pyschemaclassifier/detection/json.py
pyschemaclassifier/detection/orc.py
pyschemaclassifier/detection/parquet.py
pyschemaclassifier/detection/sampling.py
pyschemaclassifier/detection/xml.py
pyschemaclassifier/models/__init__.py
pyschemaclassifier/models/schema.py
pyschemaclassifier/utils/__init__.py
pyschemaclassifier/utils/io.py
pyschemaclassifier/utils/metrics.py
pyschemaclassifier/utils/path.py
pyschemaclassifier/writers/__init__.py
pyschemaclassifier/writers/json.py
pyschemaclassifier/writers/struct.py
pyschemaclassifier/writers/txt.py
pyschemaclassifier/writers/yaml.py
schema_classifier-1.0.1.dist-info/licenses/LICENSE
schema_classifier-1.0.1.dist-info/METADATA
schema_classifier-1.0.1.dist-info/WHEEL
schema_classifier-1.0.1.dist-info/entry_points.txt
schema_classifier-1.0.1.dist-info/top_level.txt
schema_classifier-1.0.1.dist-info/RECORD
