Metadata-Version: 2.4
Name: schema-classifier
Version: 1.0.1
Summary: Detect and infer schemas from files/dirs/DataFrames; emit YAML/JSON/TXT/Spark StructType
Author: Aashish Kumar
Keywords: schema,classifier,parquet,csv,json,delta,iceberg,hudi,avro,orc,xml,ndjson
Requires-Python: >=3.10
License-File: LICENSE
Requires-Dist: pyarrow>=12
Requires-Dist: fastavro>=1.7
Requires-Dist: zstandard>=0.20
Requires-Dist: charset-normalizer>=3.0
Requires-Dist: PyYAML>=6.0
Requires-Dist: pyorc==0.10.0
Requires-Dist: anyio>=3.6
Requires-Dist: pandas>=1.5
Requires-Dist: pyspark<3.6,>=3.3
Provides-Extra: dataframe
Requires-Dist: pandas>=1.5; extra == "dataframe"
Requires-Dist: pyspark<3.6,>=3.3; extra == "dataframe"
Provides-Extra: orc
Dynamic: license-file
